ccfx/__init__.py
ccfx/ccfx.py
ccfx/excel.py
ccfx/mssqlConnection.py
ccfx/sqliteConnection.py
ccfx/word.py
ccfx-1.0.9.dist-info/licenses/LICENSE
ccfx-1.0.9.dist-info/METADATA
ccfx-1.0.9.dist-info/WHEEL
ccfx-1.0.9.dist-info/top_level.txt
ccfx-1.0.9.dist-info/RECORD
