Metadata-Version: 2.4
Name: ccfx
Version: 1.0.9
Summary: This package simplifies regular common actions for quick prototyping in a user friendly way
Author-email: Celray James CHAWANDA <celray@chawanda.com>
License-Expression: MIT
Project-URL: Homepage, https://github.com/celray/ccfx
Classifier: Programming Language :: Python :: 3
Classifier: Operating System :: OS Independent
Requires-Python: >=3.10
License-File: LICENSE
Requires-Dist: netCDF4
Requires-Dist: yt_dlp
Requires-Dist: gdal
Requires-Dist: numpy
Requires-Dist: shapely
Requires-Dist: geopandas
Requires-Dist: pandas
Requires-Dist: xlsxwriter
Requires-Dist: pyodbc
Requires-Dist: sqlalchemy
Requires-Dist: python-docx
Requires-Dist: py7zr
Requires-Dist: mutagen
Requires-Dist: requests
Requires-Dist: tqdm
Requires-Dist: pillow
Dynamic: license-file
